arrmovs/__init__.py
arrmovs/arr.py
arrmovs/arrmov.py
arrmovs/arrmovs.py
arrmovs-0.0.3.dist-info/LICENSE.txt
arrmovs-0.0.3.dist-info/METADATA
arrmovs-0.0.3.dist-info/WHEEL
arrmovs-0.0.3.dist-info/top_level.txt
arrmovs-0.0.3.dist-info/RECORD
