Metadata-Version: 2.1
Name: arrmovs
Version: 0.0.3
Summary: Conver your INT to Array
Author: Kukushaa (Nika Beridze)
Author-email: <rexoman65@gmail.com>
Keywords: python,array,int,number,num,convert,random
Classifier: Development Status :: 1 - Planning
Classifier: Intended Audience :: Developers
Classifier: Programming Language :: Python :: 3
Classifier: Operating System :: Unix
Classifier: Operating System :: MacOS :: MacOS X
Classifier: Operating System :: Microsoft :: Windows
License-File: LICENSE.txt
